secure_bucket_construct/__init__.py
secure_bucket_construct/py.typed
secure_bucket_construct/_jsii/__init__.py
secure_bucket_construct/_jsii/secure_bucket_construct@2.1.13.jsii.tgz
secure_bucket_construct-2.1.13.dist-info/LICENSE
secure_bucket_construct-2.1.13.dist-info/METADATA
secure_bucket_construct-2.1.13.dist-info/WHEEL
secure_bucket_construct-2.1.13.dist-info/top_level.txt
secure_bucket_construct-2.1.13.dist-info/RECORD
